github_custom_actions/__about__.py
github_custom_actions/__init__.py
github_custom_actions/action_base.py
github_custom_actions/attr_dict_vars.py
github_custom_actions/env_attr_dict_vars.py
github_custom_actions/file_attr_dict_vars.py
github_custom_actions/github_vars.py
github_custom_actions/inputs_outputs.py
github_custom_actions-2.3.1.dist-info/METADATA
github_custom_actions-2.3.1.dist-info/WHEEL
github_custom_actions-2.3.1.dist-info/licenses/LICENSE.txt
github_custom_actions-2.3.1.dist-info/RECORD
