Metadata-Version: 2.4
Name: github-custom-actions
Version: 2.3.1
Summary: Python package for creating custom GitHub Actions.
Project-URL: Homepage, https://andgineer.github.io/github-custom-actions/
Project-URL: Documentation, https://andgineer.github.io/github-custom-actions/
Author-email: Andrey Sorokin <andrey@sorokin.engineer>
License: Copyright (c) 2024 Andrey Sorokin <andrey@sorokin.engineer>
License-File: LICENSE.txt
Keywords: actions,github,workflow
Classifier: License :: OSI Approved :: MIT License
Classifier: Operating System :: OS Independent
Classifier: Programming Language :: Python :: 3
Requires-Python: >=3.7
Requires-Dist: jinja2
